LICENSE
MANIFEST.in
README.rst
setup.py
bin/myremotedump
myremotedump/__init__.py
myremotedump/__main__.py
myremotedump.egg-info/PKG-INFO
myremotedump.egg-info/SOURCES.txt
myremotedump.egg-info/dependency_links.txt
myremotedump.egg-info/requires.txt
myremotedump.egg-info/top_level.txt