Metadata-Version: 1.1
Name: myremotedump
Version: 0.1.0
Summary: Dumps a firewalled MySQL database via a ssh tunnel to the remote system
Home-page: http://github.com/mtorromeo/myremotedump
Author: Massimiliano Torromeo
Author-email: massimiliano.torromeo@gmail.com
License: BSD License
Download-URL: http://github.com/mtorromeo/myremotedump/tarball/v0.1.0
Platform: UNKNOWN
Classifier: Programming Language :: Python
Classifier: Programming Language :: Python :: 3
Classifier: Development Status :: 4 - Beta
Classifier: License :: OSI Approved :: BSD License
Classifier: Operating System :: MacOS :: MacOS X
Classifier: Operating System :: POSIX :: Linux
Classifier: Operating System :: POSIX :: BSD
Classifier: Natural Language :: English
